{"data": [{"type": "scatter3d", "x": [-0.17228707711998398, -0.34673624674700637, -0.07831752337624939, 0.7238231773707874, -0.23104755146820904, 0.14382985166691417, 0.7025891842675385, -0.2163550108389599, -0.3419190574485171, -0.18357974630631418], "y": [0.6470258257523577, -0.48207978057915446, 0.09404112062668708, -0.06729553535793728, 0.5785627810844476, 0.04550424842540352, -0.07657880707971672, -0.25360520896675787, -0.23568656937040988, -0.24988807453492046], "z": [-0.09563454515174417, -0.16147032815628276, 0.656159173511767, -0.1227341539241351, -0.27807691746121393, 0.40576622640625526, -0.22403818152517624, -0.08981941532718558, -0.42046384233603906, 0.33031198396375494], "mode": "markers+text", "text": ["the", "and", "learning", "is", "neural", "modern", "artificial", "intelligence", "in", "quick", "brown", "fox", "jumps", "over", "lazy", "dog", "machine", "fascinating", "complex", "natural", "language", "processing", "involves", "analyzing", "text", "data", "networks", "power", "horses", "gallop", "gracefully", "open", "field", "how", "to", "train", "a", "network", "effectively", "transforms", "technology", "dogs", "cats", "are", "popular", "household", "pets", "programming", "python", "both", "fun", "powerful", "deep", "models", "require", "large", "datasets"], "marker": {"size": 5, "color": "blue", "opacity": 0.5}, "textposition": "top center"}], "layout": {"title": "3D Word Embeddings Visualization (PCA)", "scene": {"xaxis": {"title": "Component 1"}, "yaxis": {"title": "Component 2"}, "zaxis": {"title": "Component 3"}}, "margin": {"l": 0, "r": 0, "b": 0, "t": 50}}}